richardsonpy/__init__.py
richardsonpy/_version.py
richardsonpy/classes/__init__.py
richardsonpy/classes/appliance.py
richardsonpy/classes/electric_load.py
richardsonpy/classes/lighting.py
richardsonpy/classes/occupancy.py
richardsonpy/classes/stochastic_el_load_wrapper.py
richardsonpy/examples/__init__.py
richardsonpy/examples/example_el_load.py
richardsonpy/examples/example_occupancy.py
richardsonpy/functions/__init__.py
richardsonpy/functions/change_resolution.py
richardsonpy/functions/load_radiation.py
richardsonpy/functions/occupancy_model.py
richardsonpy/inputs/Appliances.csv
richardsonpy/inputs/LightBulbs.csv
richardsonpy/inputs/constants/ActiveAppliances_wd.csv
richardsonpy/inputs/constants/ActiveAppliances_we.csv
richardsonpy/inputs/constants/occ_start_states_wd.csv
richardsonpy/inputs/constants/occ_start_states_we.csv
richardsonpy/inputs/constants/tpm1_wd.csv
richardsonpy/inputs/constants/tpm1_we.csv
richardsonpy/inputs/constants/tpm2_wd.csv
richardsonpy/inputs/constants/tpm2_we.csv
richardsonpy/inputs/constants/tpm3_wd.csv
richardsonpy/inputs/constants/tpm3_we.csv
richardsonpy/inputs/constants/tpm4_wd.csv
richardsonpy/inputs/constants/tpm4_we.csv
richardsonpy/inputs/constants/tpm5_wd.csv
richardsonpy/inputs/constants/tpm5_we.csv
richardsonpy/inputs/weather/TRY2010_05_Jahr.dat
richardsonpy/inputs/weather/TRY2010_12_Jahr.dat
richardsonpy-0.2.2.dist-info/licenses/LICENSE
richardsonpy-0.2.2.dist-info/METADATA
richardsonpy-0.2.2.dist-info/WHEEL
richardsonpy-0.2.2.dist-info/top_level.txt
richardsonpy-0.2.2.dist-info/RECORD
