Metadata-Version: 2.4
Name: richardsonpy
Version: 0.2.2
Summary: Python version of Richardson tool to generate stochastic user and electric load profiles
Home-page: https://github.com/RWTH-EBC/richardsonpy
Author: Institute of Energy Efficient Buildings and Indoor Climate, E.ON Energy Research Center, RWTH Aachen University
License: GPL-3.0
Platform: any
Classifier: License :: OSI Approved :: GNU General Public License v3 (GPLv3)
Classifier: Programming Language :: Python :: 2.7
Classifier: Programming Language :: Python :: 3.6
Classifier: Programming Language :: Python :: 3.7
Classifier: Natural Language :: English
Classifier: Intended Audience :: Science/Research
Classifier: Topic :: Scientific/Engineering
Classifier: Topic :: Utilities
License-File: LICENSE
Requires-Dist: numpy
Requires-Dist: matplotlib
Requires-Dist: xlrd
Dynamic: author
Dynamic: classifier
Dynamic: home-page
Dynamic: license
Dynamic: license-file
Dynamic: platform
Dynamic: requires-dist
Dynamic: summary
